{"columns":[{"field":"lista","title":"Listas"},{"field":"sigla_lista","title":"Sigla Listas"},{"field":"NQN M1*","title":"NQN M1*"},{"field":"total","title":"Total"}],"data":[{"lista":"Lista N\u00ba 6 \"INTEGRACION FATU\"                                                             ","sigla_lista":"L6 INTEG.FATU","total":20,"NQN M1*":20},{"lista":"Blancos","total":7,"NQN M1*":7},{"lista":"Nulos","total":0,"NQN M1*":0},{"lista":"Recurridos","total":0,"NQN M1*":0},{"lista":"Votantes","total":27,"NQN M1*":27},{"lista":"Empadronados","total":29,"NQN M1*":29}],"data2":[{"lista":"L6 INTEG.FATU","escanos":3,"1":"(1)20","2":"(2)10","3":"(3)6.67"}],"columns2":[{"field":"lista","title":"Listas"},{"field":"escanos","title":"Cargos"},{"field":1,"title":1},{"field":2,"title":2},{"field":3,"title":3}],"titulo2":"Distribuci\u00f3n de cargos a ocupar","labels":["L6 INTEG.FATU (20 votos)"],"total":[20],"fecha":"08\/06\/2022 14:06:01","titulo":"Votos FATU Consejero\/a Directivo No docente  ","titulo_grafico":"VOTOS SOBRE MESAS CARGADAS","enviadas":"100% (1 de 1)","confirmadas":"100% (1 de 1)"}