{"data":[{"lista":"Lista N\u00ba 3 \"ECU - ENCUENTRO PARA CAMBIAR LA UNCO\"","sigla_lista":"L3 HEREDIA","ponderado":7.347779732486,"porcentaje":"45.92 %"},{"lista":"Lista N\u00ba 9 \"GESTION Y SOLIDARIDAD EN LA FACEP\"","sigla_lista":"L9 CAMADRO","ponderado":8.652220267514,"porcentaje":"54.08 %"},{"ponderado":16,"lista":"Total"}],"data2":[{"lista":"Lista N\u00ba 3 \"ECU - ENCUENTRO PARA CAMBIAR LA UNCO\"","sigla_lista":"L3 HEREDIA","total":323,"Docente":88,"Estudiantes":169,"Graduados\/as":43,"No docente":23},{"lista":"Lista N\u00ba 9 \"GESTION Y SOLIDARIDAD EN LA FACEP\"","sigla_lista":"L9 CAMADRO","total":726,"Docente":74,"Estudiantes":571,"Graduados\/as":63,"No docente":18},{"sigla_lista":"Blancos","total":100,"Docente":25,"Estudiantes":56,"Graduados\/as":14,"No docente":5},{"sigla_lista":"Nulos","total":9,"Docente":3,"Estudiantes":5,"Graduados\/as":1,"No docente":0},{"sigla_lista":"Recurridos","total":0,"Docente":0,"Estudiantes":0,"Graduados\/as":0,"No docente":0},{"sigla_lista":"Votantes","Docente":190,"Estudiantes":801,"Graduados\/as":121,"No docente":46,"total":1158},{"sigla_lista":"Empadronados","total":6116,"Docente":212,"Estudiantes":2903,"Graduados\/as":2954,"No docente":47}],"labels":["L3 HEREDIA (45.92%)","L9 CAMADRO (54.08%)"],"total":[45.92,54.08],"columns2":[{"field":"sigla_lista","title":"Sigla Listas"},{"field":"Docente","title":"Docente"},{"field":"Estudiantes","title":"Estudiantes"},{"field":"Graduados\/as","title":"Graduados\/as"},{"field":"No docente","title":"No docente"},{"field":"total","title":"Total"}],"columns":[{"field":"lista","title":"Listas"},{"field":"sigla_lista","title":"Sigla Listas"},{"field":"ponderado","title":"Ponderado"},{"field":"porcentaje","title":"Porcentaje"}],"fecha":"08\/06\/2022 14:06:01","titulo":"Votos Ponderados FACE Decano\/a","titulo2":"Votos FACE Decano\/a","enviadas":"100% (6 de 6)","confirmadas":"100% (6 de 6)","titulo_grafico":"PORCENTAJE DE VOTOS PONDERADOS SOBRE MESAS CARGADAS"}