{"data":[{"lista":"Lista N\u00ba 1 \"CONVERGENCIA UNIVERSITARIA DEL COMAHUE\"                             ","sigla_lista":"L1 GENTILE","total":11,"NQN M1*":11},{"lista":"Lista N\u00ba 2 \"FRENTE UNIVERSITARIO COMAHUE\"                                       ","sigla_lista":"L2 JURGEIT","total":19,"NQN M1*":19},{"lista":"Lista N\u00ba 3 \"PENSAR LA UNCO\"                                                     ","sigla_lista":"L3 PONCE DE L","total":22,"NQN M1*":22},{"lista":"Blancos","total":3,"NQN M1*":3},{"lista":"Nulos","total":0,"NQN M1*":0},{"lista":"Recurridos","total":0,"NQN M1*":0},{"lista":"Votantes","total":55,"NQN M1*":55},{"lista":"Empadronados","total":67,"NQN M1*":67}],"columns":[{"field":"lista","title":"Listas"},{"field":"sigla_lista","title":"Sigla"},{"field":"NQN M1*","title":"NQN M1*"},{"field":"total","title":"Total"}],"labels":["L1 GENTILE (11 votos)","L2 JURGEIT (19 votos)","L3 PONCE DE L (22 votos)"],"total":[11,19,22],"fecha":"08\/06\/2022 14:06:01","titulo":"Votos FAIF Rector\/a Docente     ","enviadas":"100% (1 de 1)","confirmadas":"100% (1 de 1)","titulo_grafico":"VOTOS SOBRE MESAS CARGADAS"}