{"data":[{"lista":"LISTA N\u00ba 1: CONFLUENCIA PARA LA ACCION                                          ","sigla_lista":"L1 CPLA","total":2,"NQN M1*":2},{"lista":"LISTA N\u00ba 2: UNIDAD DOCENTE                                                      ","sigla_lista":"L2 UDOC","total":2,"NQN M1*":2},{"lista":"LISTA N\u00ba 3: Movimiento Acad\u00e9mico Interclaustro                                  ","sigla_lista":"L3 MAI","total":47,"NQN M1*":47},{"lista":"LISTA N\u00ba 4: CONSTRUIR                                                           ","sigla_lista":"L4 CONS","total":1,"NQN M1*":1},{"lista":"LISTA N\u00ba 5: DOCENTES POR PLURALISMO E INSTITUCIONALIDAD                         ","sigla_lista":"L5 DOPI","total":0,"NQN M1*":0},{"lista":"LISTA N\u00ba 6: Encuentro para Cambiar la UNCo  ECU                                 ","sigla_lista":"L6 ECU","total":4,"NQN M1*":4},{"lista":"Blancos","total":7,"NQN M1*":7},{"lista":"Nulos","total":0,"NQN M1*":0},{"lista":"Recurridos","total":0,"NQN M1*":0},{"lista":"Votantes","total":63,"NQN M1*":63},{"lista":"Empadronados","total":73,"NQN M1*":73}],"columns":[{"field":"lista","title":"Listas"},{"field":"sigla_lista","title":"Sigla"},{"field":"NQN M1*","title":"NQN M1*"},{"field":"total","title":"Total"}],"labels":["L1 CPLA (2 votos)","L2 UDOC (2 votos)","L3 MAI (47 votos)","L4 CONS (1 votos)","L5 DOPI (0 votos)","L6 ECU (4 votos)"],"total":[2,2,47,1,0,4],"fecha":"05\/06\/2018 7:57:11","titulo":"Votos FAIF Consejero Superior Docente     ","enviadas":"100% (1 de 1)","confirmadas":"100% (1 de 1)","titulo_grafico":"VOTOS SOBRE MESAS CARGADAS"}