{"data":[{"lista":"LISTA N\u00ba 9  \"LAFAI\"                                                                       ","sigla_lista":"L9 LAFAI","total":15,"NQN M1*":15},{"lista":"Blancos","total":2,"NQN M1*":2},{"lista":"Nulos","total":0,"NQN M1*":0},{"lista":"Recurridos","total":0,"NQN M1*":0},{"lista":"Votantes","total":17,"NQN M1*":17},{"lista":"Empadronados","total":372,"NQN M1*":372}],"columns":[{"field":"lista","title":"Listas"},{"field":"sigla_lista","title":"Sigla"},{"field":"NQN M1*","title":"NQN M1*"},{"field":"total","title":"Total"}],"labels":["L9 LAFAI (15 votos)"],"total":[15],"fecha":"05\/06\/2018 7:57:11","titulo":"Votos FAIF Decano Graduados   ","enviadas":"100% (1 de 1)","confirmadas":"100% (1 de 1)","titulo_grafico":"VOTOS SOBRE MESAS CARGADAS"}