{"data":[{"lista":"Lista N\u00ba 1 \"UNIDAD FACIAS\"                                                                ","sigla_lista":"L1 ALVAREZ","total":495,"ALL M1*":31,"ALL M2*":28,"CHC M1*":48,"NQN M1*":131,"NQN M2*":136,"NQN M3*":121},{"lista":"Lista N\u00ba 7 \"CONSOLIDAR FACIAS\"                                                            ","sigla_lista":"L7 LIBERATI","total":100,"ALL M1*":16,"ALL M2*":22,"CHC M1*":5,"NQN M1*":19,"NQN M2*":22,"NQN M3*":16},{"lista":"Blancos","total":29,"ALL M1*":6,"ALL M2*":3,"CHC M1*":4,"NQN M1*":11,"NQN M2*":4,"NQN M3*":1},{"lista":"Nulos","total":14,"ALL M1*":3,"ALL M2*":3,"CHC M1*":0,"NQN M1*":3,"NQN M2*":3,"NQN M3*":2},{"lista":"Recurridos","total":0,"ALL M1*":0,"ALL M2*":0,"CHC M1*":0,"NQN M1*":0,"NQN M2*":0,"NQN M3*":0},{"lista":"Votantes","total":638,"ALL M1*":56,"ALL M2*":56,"CHC M1*":57,"NQN M1*":164,"NQN M2*":165,"NQN M3*":140},{"lista":"Empadronados","total":1782,"ALL M1*":274,"ALL M2*":255,"CHC M1*":74,"NQN M1*":398,"NQN M2*":403,"NQN M3*":378}],"columns":[{"field":"lista","title":"Listas"},{"field":"sigla_lista","title":"Sigla"},{"field":"ALL M1*","title":"ALL M1*"},{"field":"ALL M2*","title":"ALL M2*"},{"field":"CHC M1*","title":"CHC M1*"},{"field":"NQN M1*","title":"NQN M1*"},{"field":"NQN M2*","title":"NQN M2*"},{"field":"NQN M3*","title":"NQN M3*"},{"field":"total","title":"Total"}],"labels":["L1 ALVAREZ (495 votos)","L7 LIBERATI (100 votos)"],"total":[495,100],"fecha":"16\/06\/2022 10:53:01","titulo":"Votos FAAS Decano\/a Estudiantes ","enviadas":"100% (6 de 6)","confirmadas":"100% (6 de 6)","titulo_grafico":"VOTOS SOBRE MESAS CARGADAS"}