{"data":[{"lista":"Lista N\u00ba 1 \"CONVERGENCIA UNIVERSITARIA DEL COMAHUE\"                             ","sigla_lista":"L1 GENTILE","total":27,"VIE M1*":27},{"lista":"Lista N\u00ba 3 \"PENSAR LA UNCO\"                                                     ","sigla_lista":"L3 PONCE DE L","total":16,"VIE M1*":16},{"lista":"Blancos","total":1,"VIE M1*":1},{"lista":"Nulos","total":0,"VIE M1*":0},{"lista":"Recurridos","total":0,"VIE M1*":0},{"lista":"Votantes","total":44,"VIE M1*":44},{"lista":"Empadronados","total":1551,"VIE M1*":1551}],"columns":[{"field":"lista","title":"Listas"},{"field":"sigla_lista","title":"Sigla"},{"field":"VIE M1*","title":"VIE M1*"},{"field":"total","title":"Total"}],"labels":["L1 GENTILE (27 votos)","L3 PONCE DE L (16 votos)"],"total":[27,16],"fecha":"16\/06\/2022 10:53:01","titulo":"Votos CUZA Rector\/a Graduados\/as","enviadas":"100% (1 de 1)","confirmadas":"100% (1 de 1)","titulo_grafico":"VOTOS SOBRE MESAS CARGADAS"}