{"data":[{"lista":"Lista N\u00ba 1 \"CONVERGENCIA UNIVERSITARIA DEL COMAHUE\"","sigla_lista":"L1 GENTILE","ponderado":8.4556516388133,"porcentaje":"52.85 %"},{"lista":"Lista N\u00ba 3 \"PENSAR LA UNCO\"","sigla_lista":"L3 PONCE DE L","ponderado":7.5443483611867,"porcentaje":"47.15 %"},{"ponderado":16,"lista":"Total"}],"data2":[{"lista":"Lista N\u00ba 1 \"CONVERGENCIA UNIVERSITARIA DEL COMAHUE\"","sigla_lista":"L1 GENTILE","total":516,"Docente":82,"Estudiantes":365,"Graduados\/as":64,"No docente":5},{"lista":"Lista N\u00ba 3 \"PENSAR LA UNCO\"","sigla_lista":"L3 PONCE DE L","total":257,"Docente":73,"Estudiantes":133,"Graduados\/as":32,"No docente":19},{"sigla_lista":"Blancos","total":223,"Docente":26,"Estudiantes":134,"Graduados\/as":62,"No docente":1},{"sigla_lista":"Nulos","total":8,"Docente":2,"Estudiantes":6,"Graduados\/as":0,"No docente":0},{"sigla_lista":"Recurridos","total":0,"Docente":0,"Estudiantes":0,"Graduados\/as":0,"No docente":0},{"sigla_lista":"Votantes","Docente":183,"Estudiantes":638,"Graduados\/as":158,"No docente":25,"total":1004},{"sigla_lista":"Empadronados","total":3862,"Docente":212,"Estudiantes":1782,"Graduados\/as":1843,"No docente":25}],"labels":["L1 GENTILE (52.85%)","L3 PONCE DE L (47.15%)"],"total":[52.85,47.15],"columns2":[{"field":"sigla_lista","title":"Sigla Listas"},{"field":"Docente","title":"Docente"},{"field":"Estudiantes","title":"Estudiantes"},{"field":"Graduados\/as","title":"Graduados\/as"},{"field":"No docente","title":"No docente"},{"field":"total","title":"Total"}],"columns":[{"field":"lista","title":"Listas"},{"field":"sigla_lista","title":"Sigla Listas"},{"field":"ponderado","title":"Ponderado"},{"field":"porcentaje","title":"Porcentaje"}],"fecha":"16\/06\/2022 10:53:01","titulo":"Votos Ponderados FAAS Rector\/a","titulo2":"Votos FAAS Rector\/a","enviadas":"100% (13 de 13)","confirmadas":"100% (13 de 13)","titulo_grafico":"PORCENTAJE DE VOTOS PONDERADOS SOBRE MESAS CARGADAS"}